[{"rgint": "1101", "nome": "Porto Velho", "uf": "RO", "biome": "Amazônia", "label": "1101 - Porto Velho - RO"}, {"rgint": "1102", "nome": "Ji-Paraná", "uf": "RO", "biome": "Amazônia", "label": "1102 - Ji-Paraná - RO"}, {"rgint": "1201", "nome": "Rio Branco", "uf": "AC", "biome": "Amazônia", "label": "1201 - Rio Branco - AC"}, {"rgint": "1202", "nome": "Cruzeiro do Sul", "uf": "AC", "biome": "Amazônia", "label": "1202 - Cruzeiro do Sul - AC"}, {"rgint": "1301", "nome": "Manaus", "uf": "AM", "biome": "Amazônia", "label": "1301 - Manaus - AM"}, {"rgint": "1302", "nome": "Tefé", "uf": "AM", "biome": "Amazônia", "label": "1302 - Tefé - AM"}, {"rgint": "1303", "nome": "Lábrea", "uf": "AM", "biome": "Amazônia", "label": "1303 - Lábrea - AM"}, {"rgint": "1304", "nome": "Parintins", "uf": "AM", "biome": "Amazônia", "label": "1304 - Parintins - AM"}, {"rgint": "1401", "nome": "Boa Vista", "uf": "RR", "biome": "Amazônia", "label": "1401 - Boa Vista - RR"}, {"rgint": "1402", "nome": "Rorainópolis - Caracaraí", "uf": "RR", "biome": "Amazônia", "label": "1402 - Rorainópolis - Caracaraí - RR"}, {"rgint": "1501", "nome": "Belém", "uf": "PA", "biome": "Amazônia", "label": "1501 - Belém - PA"}, {"rgint": "1502", "nome": "Castanhal", "uf": "PA", "biome": "Amazônia", "label": "1502 - Castanhal - PA"}, {"rgint": "1503", "nome": "Marabá", "uf": "PA", "biome": "Amazônia", "label": "1503 - Marabá - PA"}, {"rgint": "1504", "nome": "Redenção", "uf": "PA", "biome": "Amazônia", "label": "1504 - Redenção - PA"}, {"rgint": "1505", "nome": "Santarém", "uf": "PA", "biome": "Amazônia", "label": "1505 - Santarém - PA"}, {"rgint": "1506", "nome": "Altamira", "uf": "PA", "biome": "Amazônia", "label": "1506 - Altamira - PA"}, {"rgint": "1507", "nome": "Breves", "uf": "PA", "biome": "Amazônia", "label": "1507 - Breves - PA"}, {"rgint": "1601", "nome": "Macapá", "uf": "AP", "biome": "Amazônia", "label": "1601 - Macapá - AP"}, {"rgint": "1602", "nome": "Oiapoque - Porto Grande", "uf": "AP", "biome": "Amazônia", "label": "1602 - Oiapoque - Porto Grande - AP"}, {"rgint": "1701", "nome": "Palmas", "uf": "TO", "biome": "Cerrado", "label": "1701 - Palmas - TO"}, {"rgint": "1702", "nome": "Araguaína", "uf": "TO", "biome": "Cerrado", "label": "1702 - Araguaína - TO"}, {"rgint": "1703", "nome": "Gurupi", "uf": "TO", "biome": "Cerrado", "label": "1703 - Gurupi - TO"}, {"rgint": "2101", "nome": "São Luís", "uf": "MA", "biome": "Cerrado", "label": "2101 - São Luís - MA"}, {"rgint": "2102", "nome": "Santa Inês - Bacabal", "uf": "MA", "biome": "Cerrado", "label": "2102 - Santa Inês - Bacabal - MA"}, {"rgint": "2103", "nome": "Caxias", "uf": "MA", "biome": "Cerrado", "label": "2103 - Caxias - MA"}, {"rgint": "2104", "nome": "Presidente Dutra", "uf": "MA", "biome": "Cerrado", "label": "2104 - Presidente Dutra - MA"}, {"rgint": "2105", "nome": "Imperatriz", "uf": "MA", "biome": "Cerrado", "label": "2105 - Imperatriz - MA"}, {"rgint": "2201", "nome": "Teresina", "uf": "PI", "biome": "Cerrado", "label": "2201 - Teresina - PI"}, {"rgint": "2202", "nome": "Parnaíba", "uf": "PI", "biome": "Cerrado", "label": "2202 - Parnaíba - PI"}, {"rgint": "2203", "nome": "Picos", "uf": "PI", "biome": "Cerrado", "label": "2203 - Picos - PI"}, {"rgint": "2204", "nome": "São Raimundo Nonato", "uf": "PI", "biome": "Cerrado", "label": "2204 - São Raimundo Nonato - PI"}, {"rgint": "2205", "nome": "Corrente - Bom Jesus", "uf": "PI", "biome": "Cerrado", "label": "2205 - Corrente - Bom Jesus - PI"}, {"rgint": "2206", "nome": "Floriano", "uf": "PI", "biome": "Cerrado", "label": "2206 - Floriano - PI"}, {"rgint": "2301", "nome": "Fortaleza", "uf": "CE", "biome": "Caatinga", "label": "2301 - Fortaleza - CE"}, {"rgint": "2302", "nome": "Quixadá", "uf": "CE", "biome": "Caatinga", "label": "2302 - Quixadá - CE"}, {"rgint": "2303", "nome": "Iguatu", "uf": "CE", "biome": "Caatinga", "label": "2303 - Iguatu - CE"}, {"rgint": "2304", "nome": "Juazeiro do Norte", "uf": "CE", "biome": "Caatinga", "label": "2304 - Juazeiro do Norte - CE"}, {"rgint": "2305", "nome": "Crateús", "uf": "CE", "biome": "Caatinga", "label": "2305 - Crateús - CE"}, {"rgint": "2306", "nome": "Sobral", "uf": "CE", "biome": "Caatinga", "label": "2306 - Sobral - CE"}, {"rgint": "2401", "nome": "Natal", "uf": "RN", "biome": "Caatinga", "label": "2401 - Natal - RN"}, {"rgint": "2402", "nome": "Caicó", "uf": "RN", "biome": "Caatinga", "label": "2402 - Caicó - RN"}, {"rgint": "2403", "nome": "Mossoró", "uf": "RN", "biome": "Caatinga", "label": "2403 - Mossoró - RN"}, {"rgint": "2501", "nome": "João Pessoa", "uf": "PB", "biome": "Caatinga", "label": "2501 - João Pessoa - PB"}, {"rgint": "2502", "nome": "Campina Grande", "uf": "PB", "biome": "Caatinga", "label": "2502 - Campina Grande - PB"}, {"rgint": "2503", "nome": "Patos", "uf": "PB", "biome": "Caatinga", "label": "2503 - Patos - PB"}, {"rgint": "2504", "nome": "Sousa - Cajazeiras", "uf": "PB", "biome": "Caatinga", "label": "2504 - Sousa - Cajazeiras - PB"}, {"rgint": "2601", "nome": "Recife", "uf": "PE", "biome": "Caatinga", "label": "2601 - Recife - PE"}, {"rgint": "2602", "nome": "Caruaru", "uf": "PE", "biome": "Caatinga", "label": "2602 - Caruaru - PE"}, {"rgint": "2603", "nome": "Serra Talhada", "uf": "PE", "biome": "Caatinga", "label": "2603 - Serra Talhada - PE"}, {"rgint": "2604", "nome": "Petrolina", "uf": "PE", "biome": "Caatinga", "label": "2604 - Petrolina - PE"}, {"rgint": "2701", "nome": "Maceió", "uf": "AL", "biome": "Caatinga", "label": "2701 - Maceió - AL"}, {"rgint": "2702", "nome": "Arapiraca", "uf": "AL", "biome": "Caatinga", "label": "2702 - Arapiraca - AL"}, {"rgint": "2801", "nome": "Aracaju", "uf": "SE", "biome": "Caatinga", "label": "2801 - Aracaju - SE"}, {"rgint": "2802", "nome": "Itabaiana", "uf": "SE", "biome": "Caatinga", "label": "2802 - Itabaiana - SE"}, {"rgint": "2901", "nome": "Salvador", "uf": "BA", "biome": "Cerrado", "label": "2901 - Salvador - BA"}, {"rgint": "2902", "nome": "Santo Antônio de Jesus", "uf": "BA", "biome": "Cerrado", "label": "2902 - Santo Antônio de Jesus - BA"}, {"rgint": "2903", "nome": "Ilhéus – Itabuna", "uf": "BA", "biome": "Cerrado", "label": "2903 - Ilhéus – Itabuna - BA"}, {"rgint": "2904", "nome": "Vitória da Conquista", "uf": "BA", "biome": "Cerrado", "label": "2904 - Vitória da Conquista - BA"}, {"rgint": "2905", "nome": "Guanambi", "uf": "BA", "biome": "Cerrado", "label": "2905 - Guanambi - BA"}, {"rgint": "2906", "nome": "Barreiras", "uf": "BA", "biome": "Cerrado", "label": "2906 - Barreiras - BA"}, {"rgint": "2907", "nome": "Irecê", "uf": "BA", "biome": "Cerrado", "label": "2907 - Irecê - BA"}, {"rgint": "2908", "nome": "Juazeiro", "uf": "BA", "biome": "Cerrado", "label": "2908 - Juazeiro - BA"}, {"rgint": "2909", "nome": "Paulo Afonso", "uf": "BA", "biome": "Cerrado", "label": "2909 - Paulo Afonso - BA"}, {"rgint": "2910", "nome": "Feira de Santana", "uf": "BA", "biome": "Cerrado", "label": "2910 - Feira de Santana - BA"}, {"rgint": "3101", "nome": "Belo Horizonte", "uf": "MG", "biome": "Cerrado", "label": "3101 - Belo Horizonte - MG"}, {"rgint": "3102", "nome": "Montes Claros", "uf": "MG", "biome": "Cerrado", "label": "3102 - Montes Claros - MG"}, {"rgint": "3103", "nome": "Teófilo Otoni", "uf": "MG", "biome": "Cerrado", "label": "3103 - Teófilo Otoni - MG"}, {"rgint": "3104", "nome": "Governador Valadares", "uf": "MG", "biome": "Cerrado", "label": "3104 - Governador Valadares - MG"}, {"rgint": "3105", "nome": "Ipatinga", "uf": "MG", "biome": "Cerrado", "label": "3105 - Ipatinga - MG"}, {"rgint": "3106", "nome": "Juíz de Fora", "uf": "MG", "biome": "Cerrado", "label": "3106 - Juíz de Fora - MG"}, {"rgint": "3107", "nome": "Barbacena", "uf": "MG", "biome": "Cerrado", "label": "3107 - Barbacena - MG"}, {"rgint": "3108", "nome": "Varginha", "uf": "MG", "biome": "Cerrado", "label": "3108 - Varginha - MG"}, {"rgint": "3109", "nome": "Pouso Alegre", "uf": "MG", "biome": "Cerrado", "label": "3109 - Pouso Alegre - MG"}, {"rgint": "3110", "nome": "Uberaba", "uf": "MG", "biome": "Cerrado", "label": "3110 - Uberaba - MG"}, {"rgint": "3111", "nome": "Uberlândia", "uf": "MG", "biome": "Cerrado", "label": "3111 - Uberlândia - MG"}, {"rgint": "3112", "nome": "Patos de Minas", "uf": "MG", "biome": "Cerrado", "label": "3112 - Patos de Minas - MG"}, {"rgint": "3113", "nome": "Divinópolis", "uf": "MG", "biome": "Cerrado", "label": "3113 - Divinópolis - MG"}, {"rgint": "3201", "nome": "Vitória", "uf": "ES", "biome": "Mata Atlântica", "label": "3201 - Vitória - ES"}, {"rgint": "3202", "nome": "São Mateus", "uf": "ES", "biome": "Mata Atlântica", "label": "3202 - São Mateus - ES"}, {"rgint": "3203", "nome": "Colatina", "uf": "ES", "biome": "Mata Atlântica", "label": "3203 - Colatina - ES"}, {"rgint": "3204", "nome": "Cachoeiro do Itapemirim", "uf": "ES", "biome": "Mata Atlântica", "label": "3204 - Cachoeiro do Itapemirim - ES"}, {"rgint": "3301", "nome": "Rio de Janeiro", "uf": "RJ", "biome": "Mata Atlântica", "label": "3301 - Rio de Janeiro - RJ"}, {"rgint": "3302", "nome": "Volta Redonda - Barra Mansa", "uf": "RJ", "biome": "Mata Atlântica", "label": "3302 - Volta Redonda - Barra Mansa - RJ"}, {"rgint": "3303", "nome": "Petrópolis", "uf": "RJ", "biome": "Mata Atlântica", "label": "3303 - Petrópolis - RJ"}, {"rgint": "3304", "nome": "Campos dos Goytacazes", "uf": "RJ", "biome": "Mata Atlântica", "label": "3304 - Campos dos Goytacazes - RJ"}, {"rgint": "3305", "nome": "Macaé - Rio das Ostras - Cabo Frio", "uf": "RJ", "biome": "Mata Atlântica", "label": "3305 - Macaé - Rio das Ostras - Cabo Frio - RJ"}, {"rgint": "3501", "nome": "São Paulo", "uf": "SP", "biome": "Mata Atlântica", "label": "3501 - São Paulo - SP"}, {"rgint": "3502", "nome": "Sorocaba", "uf": "SP", "biome": "Mata Atlântica", "label": "3502 - Sorocaba - SP"}, {"rgint": "3503", "nome": "Bauru", "uf": "SP", "biome": "Mata Atlântica", "label": "3503 - Bauru - SP"}, {"rgint": "3504", "nome": "Marília", "uf": "SP", "biome": "Mata Atlântica", "label": "3504 - Marília - SP"}, {"rgint": "3505", "nome": "Presidente Prudente", "uf": "SP", "biome": "Mata Atlântica", "label": "3505 - Presidente Prudente - SP"}, {"rgint": "3506", "nome": "Araçatuba", "uf": "SP", "biome": "Mata Atlântica", "label": "3506 - Araçatuba - SP"}, {"rgint": "3507", "nome": "São José do Rio Preto", "uf": "SP", "biome": "Mata Atlântica", "label": "3507 - São José do Rio Preto - SP"}, {"rgint": "3508", "nome": "Ribeirão Preto", "uf": "SP", "biome": "Mata Atlântica", "label": "3508 - Ribeirão Preto - SP"}, {"rgint": "3509", "nome": "Araraquara", "uf": "SP", "biome": "Mata Atlântica", "label": "3509 - Araraquara - SP"}, {"rgint": "3510", "nome": "Campinas", "uf": "SP", "biome": "Mata Atlântica", "label": "3510 - Campinas - SP"}, {"rgint": "3511", "nome": "São José dos Campos", "uf": "SP", "biome": "Mata Atlântica", "label": "3511 - São José dos Campos - SP"}, {"rgint": "4101", "nome": "Curitiba", "uf": "PR", "biome": "Mata Atlântica", "label": "4101 - Curitiba - PR"}, {"rgint": "4102", "nome": "Guarapuava", "uf": "PR", "biome": "Mata Atlântica", "label": "4102 - Guarapuava - PR"}, {"rgint": "4103", "nome": "Cascavel", "uf": "PR", "biome": "Mata Atlântica", "label": "4103 - Cascavel - PR"}, {"rgint": "4104", "nome": "Maringá", "uf": "PR", "biome": "Mata Atlântica", "label": "4104 - Maringá - PR"}, {"rgint": "4105", "nome": "Londrina", "uf": "PR", "biome": "Mata Atlântica", "label": "4105 - Londrina - PR"}, {"rgint": "4106", "nome": "Ponta Grossa", "uf": "PR", "biome": "Mata Atlântica", "label": "4106 - Ponta Grossa - PR"}, {"rgint": "4201", "nome": "Florianópolis", "uf": "SC", "biome": "Mata Atlântica", "label": "4201 - Florianópolis - SC"}, {"rgint": "4202", "nome": "Criciúma", "uf": "SC", "biome": "Mata Atlântica", "label": "4202 - Criciúma - SC"}, {"rgint": "4203", "nome": "Lages", "uf": "SC", "biome": "Mata Atlântica", "label": "4203 - Lages - SC"}, {"rgint": "4204", "nome": "Chapecó", "uf": "SC", "biome": "Mata Atlântica", "label": "4204 - Chapecó - SC"}, {"rgint": "4205", "nome": "Caçador", "uf": "SC", "biome": "Mata Atlântica", "label": "4205 - Caçador - SC"}, {"rgint": "4206", "nome": "Joinville", "uf": "SC", "biome": "Mata Atlântica", "label": "4206 - Joinville - SC"}, {"rgint": "4207", "nome": "Blumenau", "uf": "SC", "biome": "Mata Atlântica", "label": "4207 - Blumenau - SC"}, {"rgint": "4301", "nome": "Porto Alegre", "uf": "RS", "biome": "Pampa", "label": "4301 - Porto Alegre - RS"}, {"rgint": "4302", "nome": "Pelotas", "uf": "RS", "biome": "Pampa", "label": "4302 - Pelotas - RS"}, {"rgint": "4303", "nome": "Santa Maria", "uf": "RS", "biome": "Pampa", "label": "4303 - Santa Maria - RS"}, {"rgint": "4304", "nome": "Uruguaiana", "uf": "RS", "biome": "Pampa", "label": "4304 - Uruguaiana - RS"}, {"rgint": "4305", "nome": "Ijuí", "uf": "RS", "biome": "Pampa", "label": "4305 - Ijuí - RS"}, {"rgint": "4306", "nome": "Passo Fundo", "uf": "RS", "biome": "Pampa", "label": "4306 - Passo Fundo - RS"}, {"rgint": "4307", "nome": "Caxias do Sul", "uf": "RS", "biome": "Pampa", "label": "4307 - Caxias do Sul - RS"}, {"rgint": "4308", "nome": "Santa Cruz do Sul - Lajeado", "uf": "RS", "biome": "Pampa", "label": "4308 - Santa Cruz do Sul - Lajeado - RS"}, {"rgint": "5001", "nome": "Campo Grande", "uf": "MS", "biome": "Cerrado", "label": "5001 - Campo Grande - MS"}, {"rgint": "5002", "nome": "Dourados", "uf": "MS", "biome": "Cerrado", "label": "5002 - Dourados - MS"}, {"rgint": "5003", "nome": "Corumbá", "uf": "MS", "biome": "Cerrado", "label": "5003 - Corumbá - MS"}, {"rgint": "5101", "nome": "Cuiabá", "uf": "MT", "biome": "Cerrado", "label": "5101 - Cuiabá - MT"}, {"rgint": "5102", "nome": "Cáceres", "uf": "MT", "biome": "Cerrado", "label": "5102 - Cáceres - MT"}, {"rgint": "5103", "nome": "Sinop", "uf": "MT", "biome": "Cerrado", "label": "5103 - Sinop - MT"}, {"rgint": "5104", "nome": "Barra do Garças", "uf": "MT", "biome": "Cerrado", "label": "5104 - Barra do Garças - MT"}, {"rgint": "5105", "nome": "Rondonópolis", "uf": "MT", "biome": "Cerrado", "label": "5105 - Rondonópolis - MT"}, {"rgint": "5201", "nome": "Goiânia", "uf": "GO", "biome": "Cerrado", "label": "5201 - Goiânia - GO"}, {"rgint": "5202", "nome": "Itumbiara", "uf": "GO", "biome": "Cerrado", "label": "5202 - Itumbiara - GO"}, {"rgint": "5203", "nome": "Rio Verde", "uf": "GO", "biome": "Cerrado", "label": "5203 - Rio Verde - GO"}, {"rgint": "5204", "nome": "São Luís de Montes Belos - Iporá", "uf": "GO", "biome": "Cerrado", "label": "5204 - São Luís de Montes Belos - Iporá - GO"}, {"rgint": "5205", "nome": "Porangatu - Uruaçu", "uf": "GO", "biome": "Cerrado", "label": "5205 - Porangatu - Uruaçu - GO"}, {"rgint": "5206", "nome": "Luziânia - Águas Lindas de Goiás", "uf": "GO", "biome": "Cerrado", "label": "5206 - Luziânia - Águas Lindas de Goiás - GO"}, {"rgint": "5301", "nome": "Distrito Federal", "uf": "DF", "biome": "Cerrado", "label": "5301 - Distrito Federal - DF"}]